MANIFEST.in
README.md
pyproject.toml
setup.py
amuse_mmams.egg-info/PKG-INFO
amuse_mmams.egg-info/SOURCES.txt
amuse_mmams.egg-info/dependency_links.txt
amuse_mmams.egg-info/requires.txt
amuse_mmams.egg-info/top_level.txt
src/amuse/community/mmams/Makefile
src/amuse/community/mmams/__init__.py
src/amuse/community/mmams/_version.py
src/amuse/community/mmams/interface.cc
src/amuse/community/mmams/interface.py
src/amuse/community/mmams/src/mmas2/CMakeLists.txt
src/amuse/community/mmams/src/mmas2/src/CMakeLists.txt
src/amuse/community/mmams/src/mmas2/src/eos/CMakeLists.txt
src/amuse/community/mmams/src/mmas2/src/eos/eos.cpp
src/amuse/community/mmams/src/mmas2/src/eos/eos.h
src/amuse/community/mmams/src/mmas2/src/gsl/gslInterp.h
src/amuse/community/mmams/src/mmas2/src/gsl/gslSpline.h
src/amuse/community/mmams/src/mmas2/src/include/stdinc.h
src/amuse/community/mmams/src/mmas2/src/include/units.h
src/amuse/community/mmams/src/mmas2/src/include/vector.h
src/amuse/community/mmams/src/mmas2/src/mmas/CMakeLists.txt
src/amuse/community/mmams/src/mmas2/src/mmas/compute_energy.cpp
src/amuse/community/mmams/src/mmas2/src/mmas/compute_energy_gsl.cpp
src/amuse/community/mmams/src/mmas2/src/mmas/compute_extra.cpp
src/amuse/community/mmams/src/mmas2/src/mmas/mass_loss.cpp
src/amuse/community/mmams/src/mmas2/src/mmas/mass_loss.h
src/amuse/community/mmams/src/mmas2/src/mmas/merge_stars.cpp
src/amuse/community/mmams/src/mmas2/src/mmas/merge_stars_consistently.cpp
src/amuse/community/mmams/src/mmas2/src/mmas/merge_stars_gsl.cpp
src/amuse/community/mmams/src/mmas2/src/mmas/merge_stars_gsl_adaptive.cpp
src/amuse/community/mmams/src/mmas2/src/mmas/mixing.cpp
src/amuse/community/mmams/src/mmas2/src/mmas/mmas.h
src/amuse/community/mmams/src/mmas2/src/mmas/mmas2.cpp
src/amuse/community/mmams/src/mmas2/src/mmas/shock_heating.cpp
src/amuse/community/mmams/src/mmas2/src/mmas/solve_hse.cpp
src/amuse/community/mmams/src/mmas2/src/mmas/sort.h
src/amuse/community/mmams/src/mmas2/src/mmas/sort_entropy.cpp
src/amuse/community/mmams/src/mmas2/src/mmas/void.usm
src/amuse/community/mmams/src/mmas2/src/std/CMakeLists.txt
src/amuse/community/mmams/src/mmas2/src/std/pgetopt.cpp
